ltrans/__init__.py
ltrans/main.py
ltrans-0.1.2.dist-info/METADATA
ltrans-0.1.2.dist-info/WHEEL
ltrans-0.1.2.dist-info/entry_points.txt
ltrans-0.1.2.dist-info/top_level.txt
ltrans-0.1.2.dist-info/RECORD
