Metadata-Version: 2.4
Name: ltrans
Version: 0.1.2
Summary: A CLI tool to translate Jupyter Notebooks (ipynb) to Markdown (md) with AI, focusing on code comment translation.
Author-email: ShiWu <xyz.liu15@gmail.com>
License-Expression: MIT
Project-URL: Homepage, https://github.com/xyz-liu15/ltrans
Project-URL: Repository, https://github.com/xyz-liu15/ltrans
Keywords: llm,ai,translation,jupyter,notebook,langchain,gemini,openai
Classifier: Development Status :: 4 - Beta
Classifier: Intended Audience :: Developers
Classifier: Intended Audience :: Education
Classifier: Operating System :: OS Independent
Classifier: Programming Language :: Python :: 3
Classifier: Programming Language :: Python :: 3.9
Classifier: Programming Language :: Python :: 3.10
Classifier: Programming Language :: Python :: 3.11
Classifier: Programming Language :: Python :: 3.12
Classifier: Framework :: Jupyter
Classifier: Topic :: Software Development :: Libraries :: Python Modules
Classifier: Topic :: Text Processing
Requires-Python: >=3.9
Requires-Dist: langchain-google-genai
Requires-Dist: python-dotenv
Requires-Dist: rich
Requires-Dist: langchain-openai
Requires-Dist: typer
